mcp_polaris_ai_datainsight/server.py
mcp_polaris_ai_datainsight/tools/__init__.py
mcp_polaris_ai_datainsight/tools/datainsight_tool.py
mcp_polaris_ai_datainsight/tools/file_list_tool.py
mcp_polaris_ai_datainsight-1.0.0.dist-info/LICENSE
mcp_polaris_ai_datainsight-1.0.0.dist-info/METADATA
mcp_polaris_ai_datainsight-1.0.0.dist-info/WHEEL
mcp_polaris_ai_datainsight-1.0.0.dist-info/entry_points.txt
mcp_polaris_ai_datainsight-1.0.0.dist-info/RECORD
