Metadata-Version: 2.3
Name: mcp-polaris-ai-datainsight
Version: 1.0.0
Summary: This tool supports the extraction of text, images, and other elements from various document formats.
Keywords: polaris,datainsight,mcp
Author: Polaris Office
Author-email: ai@polarisoffice.com
Requires-Python: >=3.10,<4.0
Classifier: Programming Language :: Python :: 3
Classifier: Programming Language :: Python :: 3.10
Classifier: Programming Language :: Python :: 3.11
Classifier: Programming Language :: Python :: 3.12
Classifier: Programming Language :: Python :: 3.13
Requires-Dist: mcp[cli] (>=1.6.0,<2.0.0)
Requires-Dist: polaris-ai-datainsight (>=1.0.0,<2.0.0)
Project-URL: Homepage, https://datainsight.polarisoffice.com/
Project-URL: Repository, https://github.com/PolarisOfficeRnD/PolarisAIDataInsight/
